[
    {
        "id": 1,
        "name": "کیا",
        "logo": ""
    },
    {
        "id": 2,
        "name": "ایران خودرو",
        "logo": ""
    },
    {
        "id": 3,
        "name": "سانگ یانگ",
        "logo": ""
    },
    {
        "id": 4,
        "name": "رنو",
        "logo": ""
    },
    {
        "id": 5,
        "name": "لیفان",
        "logo": ""
    },
    {
        "id": 6,
        "name": "هیوندا",
        "logo": ""
    },
    {
        "id": 7,
        "name": "امم وی ام",
        "logo": ""
    },
    {
        "id": 8,
        "name": "جک",
        "logo": ""
    },
    {
        "id": 9,
        "name": "جیلی",
        "logo": ""
    },
    {
        "id": 10,
        "name": "چری",
        "logo": ""
    },
    {
        "id": 11,
        "name": "سوزوکی",
        "logo": ""
    },
    {
        "id": 12,
        "name": "پژو",
        "logo": ""
    },
    {
        "id": 13,
        "name": "برلیانس",
        "logo": ""
    },
    {
        "id": 14,
        "name": "سیتروئن",
        "logo": ""
    },
    {
        "id": 15,
        "name": "سایپا",
        "logo": ""
    },
    {
        "id": 16,
        "name": "نیسان",
        "logo": ""
    },
    {
        "id": 17,
        "name": "ام جی",
        "logo": ""
    },
    {
        "id": 18,
        "name": "چانگان",
        "logo": ""
    },
    {
        "id": 19,
        "name": "مزدا",
        "logo": ""
    },
    {
        "id": 20,
        "name": "بسترن",
        "logo": ""
    },
    {
        "id": 21,
        "name": "تویوتا",
        "logo": ""
    },
    {
        "id": 22,
        "name": "بایک",
        "logo": ""
    },
    {
        "id": 23,
        "name": "آلفارومئو",
        "logo": ""
    },
    {
        "id": 24,
        "name": "بی وای دی",
        "logo": ""
    },
    {
        "id": 25,
        "name": "لکسوس",
        "logo": ""
    },
    {
        "id": 26,
        "name": "دوو",
        "logo": ""
    },
    {
        "id": 27,
        "name": "دانگ فنگ",
        "logo": ""
    },
    {
        "id": 28,
        "name": "گریت وال",
        "logo": ""
    }
]